mapillary/__init__.py
mapillary/interface.py
mapillary/config/__init__.py
mapillary/config/api/__init__.py
mapillary/config/api/entities.py
mapillary/config/api/general.py
mapillary/config/api/vector_tiles.py
mapillary/controller/__init__.py
mapillary/controller/detection.py
mapillary/controller/feature.py
mapillary/controller/image.py
mapillary/controller/save.py
mapillary/models/__init__.py
mapillary/models/client.py
mapillary/models/config.py
mapillary/models/exceptions.py
mapillary/models/geojson.py
mapillary/models/logger.py
mapillary/models/api/__init__.py
mapillary/models/api/entities.py
mapillary/models/api/general.py
mapillary/models/api/vector_tiles.py
mapillary/utils/__init__.py
mapillary/utils/auth.py
mapillary/utils/extract.py
mapillary/utils/filter.py
mapillary/utils/format.py
mapillary/utils/time.py
mapillary/utils/verify.py
mapillary-1.0.14.dist-info/licenses/LICENSE
mapillary-1.0.14.dist-info/METADATA
mapillary-1.0.14.dist-info/WHEEL
mapillary-1.0.14.dist-info/top_level.txt
mapillary-1.0.14.dist-info/RECORD
