Metadata-Version: 2.4
Name: mapillary
Version: 1.0.14
Summary: A Python 3 library built on the Mapillary API v4 to facilitate retrieving and working with Mapillary data
Home-page: https://github.com/mapillary/mapillary-python-sdk
Author: Christopher Beddow
Author-email: support@mapillary.zendesk.com
License: MIT
Project-URL: Download, https://pypi.org/project/mapillary/#files
Project-URL: Release Notes, https://github.com/mapillary/mapillary-python-sdk/releases
Project-URL: Bug Tracker, https://github.com/mapillary/mapillary-python-sdk/issues
Project-URL: Source, https://github.com/mapillary/mapillary-python-sdk
Project-URL: Twitter, https://twitter.com/mapillary
Project-URL: Developer Resources, https://www.mapillary.com/developer
Project-URL: Community Forum, https://forum.mapillary.com/
Project-URL: Blog, https://blog.mapillary.com/
Project-URL: Facebook, https://www.facebook.com/mapillary/
Project-URL: Website, https://www.mapillary.com/
Platform: POSIX
Platform: MacOS X
Platform: Linux
Platform: Windows
Classifier: Development Status :: 5 - Production/Stable
Classifier: Intended Audience :: Developers
Classifier: Intended Audience :: Science/Research
Classifier: Topic :: Scientific/Engineering :: GIS
Classifier: Topic :: Scientific/Engineering :: Information Analysis
Classifier: Natural Language :: English
Classifier: Operating System :: OS Independent
Classifier: Operating System :: POSIX :: Linux
Classifier: Operating System :: Microsoft
Classifier: Operating System :: MacOS
Classifier: Operating System :: POSIX
Classifier: License :: OSI Approved :: MIT License
Classifier: Programming Language :: Python
Classifier: Programming Language :: Python :: 3
Classifier: Programming Language :: Python :: 3.5
Classifier: Programming Language :: Python :: 3.6
Classifier: Programming Language :: Python :: 3.7
Classifier: Programming Language :: Python :: 3.8
Classifier: Programming Language :: Python :: 3.9
Classifier: Programming Language :: Python :: 3.10
Classifier: Programming Language :: Python :: 3.11
Classifier: Programming Language :: Python :: 3.12
Requires-Python: >=3.0
License-File: LICENSE
Requires-Dist: mapbox-vector-tile>=2.1.0
Requires-Dist: mercantile>=1.2.1
Requires-Dist: requests>=2.25.1
Requires-Dist: vt2geojson>=0.2.1
Requires-Dist: haversine>=2.3.1
Requires-Dist: shapely>=2.1.0
Requires-Dist: turfpy>=0.0.7
Requires-Dist: geojson>=2.5.0
Dynamic: author
Dynamic: author-email
Dynamic: classifier
Dynamic: description
Dynamic: description-content-type
Dynamic: home-page
Dynamic: license
Dynamic: license-file
Dynamic: platform
Dynamic: project-url
Dynamic: requires-dist
Dynamic: requires-python
Dynamic: summary
